racer/__init__.py
racer-0.0.1.dist-info/METADATA
racer-0.0.1.dist-info/WHEEL
racer-0.0.1.dist-info/top_level.txt
racer-0.0.1.dist-info/RECORD
