Metadata-Version: 2.1
Name: racer
Version: 0.0.1
Summary: racer library.
Home-page: UNKNOWN
Author: Jim Fan
Author-email: UNKNOWN
License: GPLv3
Platform: UNKNOWN
Classifier: Development Status :: 4 - Beta
Classifier: Programming Language :: Python :: 3
